raft/__init__.py
raft/cli.py
raft/constants.py
raft/driver.py
raft/generate.py
raft/get_configs.py
raft/test_data_preprocess.py
raft/config/__init__.py
raft/config/conversation_example.yaml
raft/config/qa_example.yaml
raft/evaluation/__init__.py
raft/evaluation/evaluation.py
raft/evaluation/llm_judge.py
raft/rag/__init__.py
raft/rag/base_rag.py
raft/rag/compare_rag.py
raft/rag/constant.py
raft/rag/rag.py
raft/rag/serve_rag.py
raft/rag/test.py
raft/train/__init__.py
raft/train/train_openai.py
raft/utils/__init__.py
raft/utils/data_preprocess.py
raft/utils/data_preprocess_old.py
raft/utils/data_preprocess_v0.py
raft/utils/format.py
raft_llm-0.1.6.dist-info/METADATA
raft_llm-0.1.6.dist-info/WHEEL
raft_llm-0.1.6.dist-info/entry_points.txt
raft_llm-0.1.6.dist-info/top_level.txt
raft_llm-0.1.6.dist-info/RECORD
