Metadata-Version: 2.1
Name: raft_llm
Version: 0.1.6
Summary: A brief description of your package
Home-page: https://github.com/tianjunz/raft_llm
Author: Tianjun Zhang
Author-email: tianjunz@eecs.berkeley.edu
License: MIT
Classifier: Programming Language :: Python :: 3
Classifier: License :: OSI Approved :: MIT License
Classifier: Operating System :: OS Independent
Requires-Python: >=3.9
Requires-Dist: datasets ==2.16.1
Requires-Dist: docx ==0.2.4
Requires-Dist: fastapi ==0.111.1
Requires-Dist: langchain ==0.2.9
Requires-Dist: langchain-community ==0.2.7
Requires-Dist: langchain-core ==0.2.21
Requires-Dist: langchain-experimental ==0.0.62
Requires-Dist: langchain-openai ==0.1.17
Requires-Dist: langchain-text-splitters ==0.2.2
Requires-Dist: mdc ==1.2.1
Requires-Dist: pydantic ==2.8.2
Requires-Dist: PyPDF2 ==3.0.1
Requires-Dist: PyYAML ==6.0.1
Requires-Dist: reportlab ==4.2.2
Requires-Dist: Requests ==2.32.3
Requires-Dist: unstructured[csv,html,pdf] ==0.14.9
Requires-Dist: uvicorn ==0.30.1
Requires-Dist: faiss-cpu ==1.8.0
Requires-Dist: psutil ==6.0.0
